{
	"name": "playerLife02",
	"plugin-id": "Sprite",
	"sid": 290845926229710,
	"isGlobal": false,
	"instanceVariables": [],
	"behaviorTypes": [],
	"effectTypes": [],
	"animations": {
		"items": [
			{
				"frames": [
					{
						"width": 300,
						"height": 25,
						"originX": 1,
						"originY": 0,
						"originalSource": "",
						"exportFormat": "lossless",
						"exportQuality": 0.8,
						"imageSpriteId": 4562572,
						"useCollisionPoly": true,
						"duration": 1
					}
				],
				"sid": 886164387586888,
				"name": "Animation 1",
				"isLooping": false,
				"isPingPong": false,
				"repeatCount": 1,
				"repeatTo": 0,
				"speed": 5
			}
		],
		"subfolders": []
	}
}